pdbeccdutils/computations/__init__.py
pdbeccdutils/computations/parity_method.py
pdbeccdutils/core/__init__.py
pdbeccdutils/core/boundmolecule.py
pdbeccdutils/core/ccd_reader.py
pdbeccdutils/core/ccd_writer.py
pdbeccdutils/core/clc_reader.py
pdbeccdutils/core/clc_writer.py
pdbeccdutils/core/component.py
pdbeccdutils/core/depictions.py
pdbeccdutils/core/exceptions.py
pdbeccdutils/core/fragment_library.py
pdbeccdutils/core/models.py
pdbeccdutils/core/prd_reader.py
pdbeccdutils/core/prd_writer.py
pdbeccdutils/data/coordgen_templates/templates.mae
pdbeccdutils/data/fragment_library.tsv
pdbeccdutils/data/general_templates/adamantane.sdf
pdbeccdutils/data/general_templates/cube.sdf
pdbeccdutils/data/general_templates/decahydrocorrin.sdf
pdbeccdutils/data/general_templates/hem.sdf
pdbeccdutils/data/general_templates/nonbornane.sdf
pdbeccdutils/data/general_templates/phorbine.sdf
pdbeccdutils/data/general_templates/porphin.sdf
pdbeccdutils/data/general_templates/porphycene.sdf
pdbeccdutils/data/general_templates/ru_complex.sdf
pdbeccdutils/data/general_templates/ru_complex2.sdf
pdbeccdutils/helpers/__init__.py
pdbeccdutils/helpers/cif_tools.py
pdbeccdutils/helpers/conversions.py
pdbeccdutils/helpers/drawing.py
pdbeccdutils/helpers/helper.py
pdbeccdutils/helpers/mol_tools.py
pdbeccdutils/scripts/__init__.py
pdbeccdutils/scripts/boundmolecule_cli.py
pdbeccdutils/scripts/process_components_cif_cli.py
pdbeccdutils/scripts/setup_pubchem_library_cli.py
pdbeccdutils/tests/ccd_mmcif_test_files/UNL.cif
pdbeccdutils/tests/ccd_mmcif_test_files/depiction_test/0KA.cif
pdbeccdutils/tests/ccd_mmcif_test_files/depiction_test/11R.cif
pdbeccdutils/tests/ccd_mmcif_test_files/depiction_test/1CL.cif
pdbeccdutils/tests/ccd_mmcif_test_files/depiction_test/6KK.cif
pdbeccdutils/tests/ccd_mmcif_test_files/depiction_test/ADM.cif
pdbeccdutils/tests/ccd_mmcif_test_files/depiction_test/AXM.cif
pdbeccdutils/tests/ccd_mmcif_test_files/depiction_test/G2O.cif
pdbeccdutils-1.0.0.dist-info/LICENSE
pdbeccdutils-1.0.0.dist-info/METADATA
pdbeccdutils-1.0.0.dist-info/WHEEL
pdbeccdutils-1.0.0.dist-info/entry_points.txt
pdbeccdutils-1.0.0.dist-info/RECORD
