Metadata-Version: 2.3
Name: pdbeccdutils
Version: 1.0.0
Summary: Toolkit to parse and process small molecules in wwPDB
License: Apache License 2.0.
Keywords: PDB,ligand,small molecule,complex,CCD,PRD,CLC
Author: Protein Data Bank in Europe
Author-email: pdbehelp@ebi.ac.uk
Requires-Python: >=3.10,<4
Classifier: Development Status :: 5 - Production/Stable
Classifier: Intended Audience :: Developers
Classifier: Intended Audience :: Science/Research
Classifier: License :: OSI Approved :: Apache Software License
Classifier: License :: Other/Proprietary License
Classifier: Operating System :: MacOS
Classifier: Operating System :: Microsoft :: Windows
Classifier: Operating System :: POSIX
Classifier: Operating System :: Unix
Classifier: Programming Language :: Python
Classifier: Programming Language :: Python :: 3
Classifier: Programming Language :: Python :: 3.10
Classifier: Programming Language :: Python :: 3.11
Classifier: Programming Language :: Python :: 3.12
Classifier: Programming Language :: Python :: 3.13
Classifier: Programming Language :: Python :: 3.9
Classifier: Programming Language :: Python :: Implementation :: CPython
Classifier: Programming Language :: Python :: Implementation :: PyPy
Classifier: Topic :: Scientific/Engineering :: Bio-Informatics
Classifier: Topic :: Scientific/Engineering :: Chemistry
Requires-Dist: gemmi (>=0.6.6)
Requires-Dist: networkx (>=3.3)
Requires-Dist: numpy (>=1.26.4)
Requires-Dist: pillow (>=10.4.0)
Requires-Dist: rdkit (>=2023.9.6)
Requires-Dist: requests (>=2.32.3)
Requires-Dist: scipy (>=1.14.1)
Project-URL: Documentation, https://pdbeurope.github.io/ccdutils/
Project-URL: Repository, https://github.com/PDBeurope/ccdutils
